pharmaliu2/__init__.py
pharmaliu2/analysis.py
pharmaliu2-0.1.0.dist-info/LICENSE
pharmaliu2-0.1.0.dist-info/METADATA
pharmaliu2-0.1.0.dist-info/WHEEL
pharmaliu2-0.1.0.dist-info/top_level.txt
pharmaliu2-0.1.0.dist-info/RECORD
