Metadata-Version: 2.1
Name: pharmaliu2
Version: 0.1.0
Summary: A package for pharmacokinetic modeling and parameter estimation
Author: liucann
Author-email: liucan18726995722@163.com
License: UNKNOWN
Platform: UNKNOWN
Classifier: Programming Language :: Python :: 3
Classifier: License :: OSI Approved :: MIT License
Classifier: Operating System :: OS Independent
Requires-Python: >=3.6
License-File: LICENSE
Requires-Dist: numpy
Requires-Dist: pandas
Requires-Dist: scipy
